jankins/__init__.py
jankins/__main__.py
jankins/cache.py
jankins/config.py
jankins/errors.py
jankins/logging_utils.py
jankins/metrics.py
jankins/server.py
jankins/analyzers/__init__.py
jankins/analyzers/base.py
jankins/analyzers/gradle.py
jankins/analyzers/maven.py
jankins/analyzers/npm.py
jankins/formatters/__init__.py
jankins/formatters/base.py
jankins/formatters/token_aware.py
jankins/jenkins/__init__.py
jankins/jenkins/adapter.py
jankins/jenkins/blueocean.py
jankins/jenkins/progressive.py
jankins/jenkins/testresults.py
jankins/mcp/__init__.py
jankins/mcp/protocol.py
jankins/mcp/stdio_transport.py
jankins/mcp/transport.py
jankins/middleware/__init__.py
jankins/middleware/ratelimit.py
jankins/prompts/__init__.py
jankins/prompts/templates.py
jankins/tools/__init__.py
jankins/tools/advanced.py
jankins/tools/builds.py
jankins/tools/health.py
jankins/tools/jobs.py
jankins/tools/logs.py
jankins/tools/scm.py
jankins/tools/tests.py
jankins-1.3.0.dist-info/licenses/LICENSE
jankins-1.3.0.dist-info/METADATA
jankins-1.3.0.dist-info/WHEEL
jankins-1.3.0.dist-info/entry_points.txt
jankins-1.3.0.dist-info/top_level.txt
jankins-1.3.0.dist-info/RECORD
