Metadata-Version: 2.4
Name: jankins
Version: 1.3.0
Summary: Token-optimized Jenkins MCP server with smart log handling and advanced triage
Author: jankins contributors
License: MIT
Keywords: jenkins,mcp,model-context-protocol,ci-cd,devops
Classifier: Development Status :: 3 - Alpha
Classifier: Intended Audience :: Developers
Classifier: License :: OSI Approved :: MIT License
Classifier: Programming Language :: Python :: 3
Classifier: Programming Language :: Python :: 3.10
Classifier: Programming Language :: Python :: 3.11
Classifier: Programming Language :: Python :: 3.12
Requires-Python: >=3.10
License-File: LICENSE
Requires-Dist: python-jenkins>=1.8.0
Requires-Dist: httpx>=0.27.0
Requires-Dist: sse-starlette>=2.0.0
Requires-Dist: starlette>=0.37.0
Requires-Dist: uvicorn>=0.29.0
Requires-Dist: pydantic>=2.7.0
Requires-Dist: pydantic-settings>=2.2.0
Requires-Dist: click>=8.1.0
Requires-Dist: tiktoken>=0.7.0
Provides-Extra: dev
Requires-Dist: pytest>=8.0.0; extra == "dev"
Requires-Dist: pytest-asyncio>=0.23.0; extra == "dev"
Requires-Dist: pytest-httpx>=0.30.0; extra == "dev"
Requires-Dist: pytest-cov>=5.0.0; extra == "dev"
Requires-Dist: pytest-mock>=3.14.0; extra == "dev"
Requires-Dist: pytest-timeout>=2.3.0; extra == "dev"
Requires-Dist: pytest-xdist>=3.6.0; extra == "dev"
Requires-Dist: hypothesis>=6.100.0; extra == "dev"
Requires-Dist: black>=24.0.0; extra == "dev"
Requires-Dist: ruff>=0.4.0; extra == "dev"
Requires-Dist: mypy>=1.10.0; extra == "dev"
Requires-Dist: bandit[toml]>=1.7.8; extra == "dev"
Requires-Dist: safety>=3.2.0; extra == "dev"
Requires-Dist: pre-commit>=3.7.0; extra == "dev"
Requires-Dist: tox>=4.15.0; extra == "dev"
Requires-Dist: python-semantic-release>=9.0.0; extra == "dev"
Dynamic: license-file
